SSHCustodian-0.2.6.dist-info/DESCRIPTION.rst
SSHCustodian-0.2.6.dist-info/METADATA
SSHCustodian-0.2.6.dist-info/RECORD
SSHCustodian-0.2.6.dist-info/WHEEL
SSHCustodian-0.2.6.dist-info/metadata.json
SSHCustodian-0.2.6.dist-info/top_level.txt
sshcustodian/__init__.py
sshcustodian/sshcustodian.py
sshcustodian/vasp/__init__.py
sshcustodian/vasp/sshjobs.py
