Metadata-Version: 2.0
Name: SSHCustodian
Version: 0.2.6
Summary: A modification to the Custodian class in custodian (github.com/materialsproject/custodian) to allow for copying the temp_dir to other compute nodes via ssh.
Home-page: https://github.com/jkglasbrenner/sshcustodian
Author: James K. Glasbrenner
Author-email: jkglasbrenner@gmail.com
License: MIT
Download-URL: https://github.com/jkglasbrenner/sshcustodian/tarball/0.2.6
Keywords: custodian DFT VASP materials hpc queue management
Platform: UNKNOWN
Classifier: Intended Audience :: Science/Research
Classifier: License :: OSI Approved :: MIT License
Classifier: Programming Language :: Python :: 2.7
Classifier: Programming Language :: Python :: 3.5
Requires-Dist: custodian
Requires-Dist: monty
Requires-Dist: six
